{"version":1,"resource":"file:///home/carlos/.config/conky/ConkyWidgets/conky-widgets","entries":[{"id":"PYYm","timestamp":1701988214621},{"id":"3r07","timestamp":1701988247780},{"id":"9NfC","timestamp":1701988279252},{"id":"pMl5","timestamp":1701988326044},{"id":"hTXY","timestamp":1701988345436},{"id":"Mnvh","timestamp":1701988976921},{"id":"fOak","timestamp":1701988988920},{"id":"cqcb","timestamp":1701989005617},{"id":"b1DQ","timestamp":1701989036799},{"id":"0jpQ","source":"undoRedo.source","timestamp":1701989042225},{"id":"wXVb","timestamp":1701989060327},{"id":"62jC","timestamp":1701989129032},{"id":"nzeq","timestamp":1701989140735},{"id":"Bebf","timestamp":1701989164744},{"id":"1fNw","timestamp":1701989290535},{"id":"7fwc","timestamp":1701989315551}]}